JoDBS_Tools/BotSetup.py
JoDBS_Tools/Database.py
JoDBS_Tools/Decorators.py
JoDBS_Tools/YouTube.py
JoDBS_Tools/__init__.py
JoDBS_Tools/utils.py
JoDBS_Tools-0.2.4.dist-info/LICENSE
JoDBS_Tools-0.2.4.dist-info/METADATA
JoDBS_Tools-0.2.4.dist-info/WHEEL
JoDBS_Tools-0.2.4.dist-info/top_level.txt
JoDBS_Tools-0.2.4.dist-info/RECORD
