Metadata-Version: 2.1
Name: JoDBS_Tools
Version: 0.2.4
Summary: A utility library by JoDBS
Home-page: https://github.com/JoDBS/JoDBS_Tools
Author: JoDBS
Author-email: 
Classifier: Programming Language :: Python :: 3
Classifier: License :: OSI Approved :: MIT License
Classifier: Operating System :: OS Independent
Requires-Python: >=3.12
License-File: LICENSE
Requires-Dist: pymongo
Requires-Dist: nextcord
Requires-Dist: python-dotenv
Requires-Dist: requests
